opentrons_shared_data/__init__.py
opentrons_shared_data/_version.py
opentrons_shared_data/load.py
opentrons_shared_data/py.typed
opentrons_shared_data/command/__init__.py
opentrons_shared_data/deck/__init__.py
opentrons_shared_data/deck/types.py
opentrons_shared_data/errors/__init__.py
opentrons_shared_data/errors/categories.py
opentrons_shared_data/errors/codes.py
opentrons_shared_data/errors/exceptions.py
opentrons_shared_data/gripper/__init__.py
opentrons_shared_data/gripper/constants.py
opentrons_shared_data/gripper/gripper_definition.py
opentrons_shared_data/labware/__init__.py
opentrons_shared_data/labware/constants.py
opentrons_shared_data/labware/labware_definition.py
opentrons_shared_data/labware/types.py
opentrons_shared_data/liquid_classes/__init__.py
opentrons_shared_data/liquid_classes/liquid_class_definition.py
opentrons_shared_data/liquid_classes/types.py
opentrons_shared_data/module/__init__.py
opentrons_shared_data/module/types.py
opentrons_shared_data/pipette/__init__.py
opentrons_shared_data/pipette/dev_types.py
opentrons_shared_data/pipette/file_operation_helpers.py
opentrons_shared_data/pipette/load_data.py
opentrons_shared_data/pipette/model_constants.py
opentrons_shared_data/pipette/mutable_configurations.py
opentrons_shared_data/pipette/pipette_definition.py
opentrons_shared_data/pipette/pipette_load_name_conversions.py
opentrons_shared_data/pipette/types.py
opentrons_shared_data/pipette/ul_per_mm.py
opentrons_shared_data/pipette/scripts/__init__.py
opentrons_shared_data/pipette/scripts/build_json_script.py
opentrons_shared_data/pipette/scripts/update_configuration_files.py
opentrons_shared_data/protocol/__init__.py
opentrons_shared_data/protocol/constants.py
opentrons_shared_data/protocol/types.py
opentrons_shared_data/protocol/models/__init__.py
opentrons_shared_data/protocol/models/protocol_schema_v6.py
opentrons_shared_data/protocol/models/protocol_schema_v7.py
opentrons_shared_data/protocol/models/protocol_schema_v8.py
opentrons_shared_data-8.7.0.dist-info/METADATA
opentrons_shared_data-8.7.0.dist-info/WHEEL
opentrons_shared_data-8.7.0.dist-info/licenses/LICENSE
opentrons_shared_data-8.7.0.dist-info/RECORD
